odoo/addons/mail_post_defer/README.rst
odoo/addons/mail_post_defer/__init__.py
odoo/addons/mail_post_defer/__manifest__.py
odoo/addons/mail_post_defer/hooks.py
odoo/addons/mail_post_defer/i18n/es.po
odoo/addons/mail_post_defer/i18n/it.po
odoo/addons/mail_post_defer/i18n/mail_post_defer.pot
odoo/addons/mail_post_defer/models/__init__.py
odoo/addons/mail_post_defer/models/mail_message.py
odoo/addons/mail_post_defer/models/mail_message_schedule.py
odoo/addons/mail_post_defer/models/mail_thread.py
odoo/addons/mail_post_defer/readme/CONFIGURE.md
odoo/addons/mail_post_defer/readme/CONTRIBUTORS.md
odoo/addons/mail_post_defer/readme/DESCRIPTION.md
odoo/addons/mail_post_defer/readme/ROADMAP.md
odoo/addons/mail_post_defer/readme/USAGE.md
odoo/addons/mail_post_defer/static/description/icon.png
odoo/addons/mail_post_defer/static/description/index.html
odoo/addons/mail_post_defer/static/src/js/message.esm.js
odoo/addons/mail_post_defer/tests/__init__.py
odoo/addons/mail_post_defer/tests/test_install.py
odoo/addons/mail_post_defer/tests/test_mail.py
odoo_addon_mail_post_defer-18.0.1.0.0.4.dist-info/METADATA
odoo_addon_mail_post_defer-18.0.1.0.0.4.dist-info/WHEEL
odoo_addon_mail_post_defer-18.0.1.0.0.4.dist-info/top_level.txt
odoo_addon_mail_post_defer-18.0.1.0.0.4.dist-info/RECORD
